djatalist/__about__.py
djatalist/__init__.py
djatalist/widgets.py
djatalist/templates/multiple.html
djatalist-0.0.1.dist-info/METADATA
djatalist-0.0.1.dist-info/WHEEL
djatalist-0.0.1.dist-info/licenses/LICENSE.txt
djatalist-0.0.1.dist-info/RECORD
