Metadata-Version: 2.1
Name: djatalist
Version: 0.0.1
Project-URL: Documentation, https://github.com/d-flood/djatalist#readme
Project-URL: Issues, https://github.com/d-flood/djatalist/issues
Project-URL: Source, https://github.com/d-flood/djatalist
Author-email: David Flood <davidfloodii@gmail.com>
License-Expression: MIT
License-File: LICENSE.txt
Classifier: Development Status :: 4 - Beta
Classifier: Programming Language :: Python
Classifier: Programming Language :: Python :: 3.10
Classifier: Programming Language :: Python :: 3.11
Classifier: Programming Language :: Python :: 3.12
Classifier: Programming Language :: Python :: Implementation :: CPython
Requires-Python: >=3.7
Requires-Dist: django==4.2.7
